bigdl/__init__.py
bigdl/nano/__init__.py
bigdl/nano/openvino.py
bigdl/nano/automl/__init__.py
bigdl/nano/automl/hpo/__init__.py
bigdl/nano/automl/hpo/backend.py
bigdl/nano/automl/hpo/callgraph.py
bigdl/nano/automl/hpo/config.py
bigdl/nano/automl/hpo/decorator.py
bigdl/nano/automl/hpo/search.py
bigdl/nano/automl/hpo/space.py
bigdl/nano/automl/hpo/visualization.py
bigdl/nano/automl/pytorch/__init__.py
bigdl/nano/automl/pytorch/_helper.py
bigdl/nano/automl/pytorch/hposearcher.py
bigdl/nano/automl/pytorch/objective.py
bigdl/nano/automl/tf/__init__.py
bigdl/nano/automl/tf/mixin.py
bigdl/nano/automl/tf/objective.py
bigdl/nano/automl/tf/keras/Model.py
bigdl/nano/automl/tf/keras/Sequential.py
bigdl/nano/automl/tf/keras/__init__.py
bigdl/nano/automl/utils/__init__.py
bigdl/nano/automl/utils/edict.py
bigdl/nano/automl/utils/parallel.py
bigdl/nano/automl/utils/parallel_worker.py
bigdl/nano/automl/utils/proxy.py
bigdl/nano/automl/utils/register_modules.py
bigdl/nano/deps/__init__.py
bigdl/nano/deps/automl/__init__.py
bigdl/nano/deps/automl/hpo_api.py
bigdl/nano/deps/automl/optuna_backend.py
bigdl/nano/deps/horovod/__init__.py
bigdl/nano/deps/horovod/distributed_utils_horovod.py
bigdl/nano/deps/horovod/horovod_api.py
bigdl/nano/deps/horovod/horovod_worker.py
bigdl/nano/deps/horovod/multiprocs_backend.py
bigdl/nano/deps/ipex/__init__.py
bigdl/nano/deps/ipex/ipex_api.py
bigdl/nano/deps/ipex/ipex_inference_bf16_model.py
bigdl/nano/deps/ipex/ipex_inference_model.py
bigdl/nano/deps/ipex/ipex_inference_xpu_model.py
bigdl/nano/deps/ipex/ipex_quantization_model.py
bigdl/nano/deps/neural_compressor/__init__.py
bigdl/nano/deps/neural_compressor/inc_api.py
bigdl/nano/deps/neural_compressor/inc_api_2.py
bigdl/nano/deps/neural_compressor/core/__init__.py
bigdl/nano/deps/neural_compressor/core/base_metric.py
bigdl/nano/deps/neural_compressor/core/quantization.py
bigdl/nano/deps/neural_compressor/onnx/__init__.py
bigdl/nano/deps/neural_compressor/onnx/metric.py
bigdl_nano-2.4.0.dist-info/METADATA
bigdl_nano-2.4.0.dist-info/WHEEL
bigdl_nano-2.4.0.dist-info/entry_points.txt
bigdl_nano-2.4.0.dist-info/top_level.txt
bigdl_nano-2.4.0.dist-info/RECORD
