Metadata-Version: 2.1
Name: bigdl-nano
Version: 2.4.0
Summary: High-performance scalable acceleration components for intel.
Home-page: https://github.com/intel-analytics/BigDL
Author: BigDL Authors
Author-email: bigdl-user-group@googlegroups.com
License: UNKNOWN
Platform: UNKNOWN
Requires-Dist: cloudpickle
Requires-Dist: protobuf (==3.19.5)
Requires-Dist: py-cpuinfo
Requires-Dist: pyyaml
Requires-Dist: packaging
Requires-Dist: sigfig
Requires-Dist: setuptools (<66)
Requires-Dist: intel-openmp ; platform_machine == "x86_64" or platform_machine == "AMD64"
Provides-Extra: diffusion_113
Requires-Dist: torch (==1.13.1) ; extra == 'diffusion_113'
Requires-Dist: torchvision (==0.14.1) ; extra == 'diffusion_113'
Requires-Dist: pytorch-lightning (==1.6.4) ; extra == 'diffusion_113'
Requires-Dist: torchmetrics (==0.11.0) ; extra == 'diffusion_113'
Requires-Dist: opencv-python-headless ; extra == 'diffusion_113'
Requires-Dist: PyTurboJPEG ; extra == 'diffusion_113'
Requires-Dist: opencv-transforms ; extra == 'diffusion_113'
Requires-Dist: cryptography (==41.0.3) ; extra == 'diffusion_113'
Requires-Dist: diffusers (==0.14.0) ; extra == 'diffusion_113'
Requires-Dist: transformers (==4.34.0) ; extra == 'diffusion_113'
Requires-Dist: intel-extension-for-pytorch (==1.13.100) ; (platform_system == "Linux") and extra == 'diffusion_113'
Provides-Extra: inference
Requires-Dist: onnx (==1.12.0) ; extra == 'inference'
Requires-Dist: onnxruntime (==1.12.1) ; extra == 'inference'
Requires-Dist: openvino-dev (==2022.3.0) ; extra == 'inference'
Requires-Dist: scipy (<=1.10.1) ; extra == 'inference'
Requires-Dist: onnxruntime-extensions (==0.3.1) ; ((platform_machine == "x86_64" or platform_machine == "AMD64") and platform_system == "Darwin") and extra == 'inference'
Requires-Dist: onnxsim (==0.4.1) ; ((platform_machine == "x86_64" or platform_machine == "AMD64") and platform_system == "Darwin") and extra == 'inference'
Requires-Dist: onnxruntime-extensions (==0.7.0) ; (platform_system != "Darwin") and extra == 'inference'
Requires-Dist: onnxsim (==0.4.8) ; (platform_system != "Darwin") and extra == 'inference'
Requires-Dist: neural-compressor (==2.0) ; (platform_system != "Windows") and extra == 'inference'
Provides-Extra: pytorch
Requires-Dist: torch (==1.13.1) ; extra == 'pytorch'
Requires-Dist: torchvision (==0.14.1) ; extra == 'pytorch'
Requires-Dist: pytorch-lightning (==1.6.4) ; extra == 'pytorch'
Requires-Dist: torchmetrics (==0.11.0) ; extra == 'pytorch'
Requires-Dist: opencv-python-headless ; extra == 'pytorch'
Requires-Dist: PyTurboJPEG ; extra == 'pytorch'
Requires-Dist: opencv-transforms ; extra == 'pytorch'
Requires-Dist: cryptography (==41.0.3) ; extra == 'pytorch'
Requires-Dist: intel-extension-for-pytorch (==1.13.100) ; (platform_system == "Linux") and extra == 'pytorch'
Provides-Extra: pytorch_110
Requires-Dist: torch (==1.10.1) ; extra == 'pytorch_110'
Requires-Dist: torchvision (==0.11.2) ; extra == 'pytorch_110'
Requires-Dist: pytorch-lightning (==1.6.4) ; extra == 'pytorch_110'
Requires-Dist: torchmetrics (==0.11.0) ; extra == 'pytorch_110'
Requires-Dist: opencv-python-headless ; extra == 'pytorch_110'
Requires-Dist: PyTurboJPEG ; extra == 'pytorch_110'
Requires-Dist: opencv-transforms ; extra == 'pytorch_110'
Requires-Dist: cryptography (==41.0.3) ; extra == 'pytorch_110'
Requires-Dist: intel-extension-for-pytorch (==1.10.100) ; (platform_system == "Linux") and extra == 'pytorch_110'
Provides-Extra: pytorch_111
Requires-Dist: torch (==1.11.0) ; extra == 'pytorch_111'
Requires-Dist: torchvision (==0.12.0) ; extra == 'pytorch_111'
Requires-Dist: pytorch-lightning (==1.6.4) ; extra == 'pytorch_111'
Requires-Dist: torchmetrics (==0.11.0) ; extra == 'pytorch_111'
Requires-Dist: opencv-python-headless ; extra == 'pytorch_111'
Requires-Dist: PyTurboJPEG ; extra == 'pytorch_111'
Requires-Dist: opencv-transforms ; extra == 'pytorch_111'
Requires-Dist: cryptography (==41.0.3) ; extra == 'pytorch_111'
Requires-Dist: intel-extension-for-pytorch (==1.11.0) ; (platform_system == "Linux") and extra == 'pytorch_111'
Provides-Extra: pytorch_112
Requires-Dist: torch (==1.12.1) ; extra == 'pytorch_112'
Requires-Dist: torchvision (==0.13.1) ; extra == 'pytorch_112'
Requires-Dist: pytorch-lightning (==1.6.4) ; extra == 'pytorch_112'
Requires-Dist: torchmetrics (==0.11.0) ; extra == 'pytorch_112'
Requires-Dist: opencv-python-headless ; extra == 'pytorch_112'
Requires-Dist: PyTurboJPEG ; extra == 'pytorch_112'
Requires-Dist: opencv-transforms ; extra == 'pytorch_112'
Requires-Dist: cryptography (==41.0.3) ; extra == 'pytorch_112'
Requires-Dist: intel-extension-for-pytorch (==1.12.300) ; (platform_system == "Linux") and extra == 'pytorch_112'
Provides-Extra: pytorch_113
Requires-Dist: torch (==1.13.1) ; extra == 'pytorch_113'
Requires-Dist: torchvision (==0.14.1) ; extra == 'pytorch_113'
Requires-Dist: pytorch-lightning (==1.6.4) ; extra == 'pytorch_113'
Requires-Dist: torchmetrics (==0.11.0) ; extra == 'pytorch_113'
Requires-Dist: opencv-python-headless ; extra == 'pytorch_113'
Requires-Dist: PyTurboJPEG ; extra == 'pytorch_113'
Requires-Dist: opencv-transforms ; extra == 'pytorch_113'
Requires-Dist: cryptography (==41.0.3) ; extra == 'pytorch_113'
Requires-Dist: intel-extension-for-pytorch (==1.13.100) ; (platform_system == "Linux") and extra == 'pytorch_113'
Provides-Extra: pytorch_113_xpu
Requires-Dist: torch (==1.13.0a0+git6c9b55e) ; extra == 'pytorch_113_xpu'
Requires-Dist: torchvision (==0.14.1a0) ; extra == 'pytorch_113_xpu'
Requires-Dist: pytorch-lightning (==1.6.4) ; extra == 'pytorch_113_xpu'
Requires-Dist: torchmetrics (==0.11.0) ; extra == 'pytorch_113_xpu'
Requires-Dist: opencv-python-headless ; extra == 'pytorch_113_xpu'
Requires-Dist: PyTurboJPEG ; extra == 'pytorch_113_xpu'
Requires-Dist: opencv-transforms ; extra == 'pytorch_113_xpu'
Requires-Dist: cryptography (==41.0.3) ; extra == 'pytorch_113_xpu'
Requires-Dist: intel-extension-for-pytorch (==1.13.120+xpu) ; (platform_system == "Linux") and extra == 'pytorch_113_xpu'
Provides-Extra: pytorch_20
Requires-Dist: torch (==2.0.0) ; extra == 'pytorch_20'
Requires-Dist: torchvision (==0.15.1) ; extra == 'pytorch_20'
Requires-Dist: pytorch-lightning (==1.6.4) ; extra == 'pytorch_20'
Requires-Dist: torchmetrics (==0.11.0) ; extra == 'pytorch_20'
Requires-Dist: opencv-python-headless ; extra == 'pytorch_20'
Requires-Dist: PyTurboJPEG ; extra == 'pytorch_20'
Requires-Dist: opencv-transforms ; extra == 'pytorch_20'
Requires-Dist: cryptography (==41.0.3) ; extra == 'pytorch_20'
Requires-Dist: intel-extension-for-pytorch (==2.0.100) ; (platform_system == "Linux") and extra == 'pytorch_20'
Provides-Extra: pytorch_20_xpu
Requires-Dist: torch (==2.0.1a0) ; extra == 'pytorch_20_xpu'
Requires-Dist: torchvision (==0.15.2a0) ; extra == 'pytorch_20_xpu'
Requires-Dist: intel-extension-for-pytorch (==2.0.110+xpu) ; (platform_system == "Linux") and extra == 'pytorch_20_xpu'
Provides-Extra: pytorch_nightly
Requires-Dist: torch (~=1.14.0.dev) ; extra == 'pytorch_nightly'
Requires-Dist: torchvision (~=0.15.0.dev) ; extra == 'pytorch_nightly'
Requires-Dist: pytorch-lightning (==1.6.4) ; extra == 'pytorch_nightly'
Requires-Dist: torchmetrics (==0.11.0) ; extra == 'pytorch_nightly'
Requires-Dist: opencv-python-headless ; extra == 'pytorch_nightly'
Requires-Dist: PyTurboJPEG ; extra == 'pytorch_nightly'
Requires-Dist: opencv-transforms ; extra == 'pytorch_nightly'
Requires-Dist: cryptography (==41.0.3) ; extra == 'pytorch_nightly'
